pcfl/__init__.py
pcfl/__main__.py
pcfl/core/__init__.py
pcfl/core/algorithm.py
pcfl/core/exceptions.py
pcfl/core/output.py
pcfl/core/parser.py
pcfl/func.py
pcfl/interface.py
pcfl/validator.py
pcfl-1.0.0.dist-info/LICENSE
pcfl-1.0.0.dist-info/METADATA
pcfl-1.0.0.dist-info/WHEEL
pcfl-1.0.0.dist-info/RECORD
