Metadata-Version: 2.1
Name: pcfl
Version: 1.0.0
Summary: Pinao Compensator for FLstudio
Home-page: https://github.com/skywinz/pcfl
License: MIT
Author: recoma
Author-email: seokbong60@gmail.com
Requires-Python: >=3.10,<4.0
Classifier: Intended Audience :: End Users/Desktop
Classifier: License :: OSI Approved :: MIT License
Classifier: Operating System :: POSIX :: Linux
Classifier: Programming Language :: Python :: 3
Classifier: Programming Language :: Python :: 3.10
Classifier: Programming Language :: Python :: 3.11
Classifier: Programming Language :: Python :: 3.12
Classifier: Topic :: Software Development :: Libraries :: Python Modules
Classifier: Topic :: Utilities
Requires-Dist: mido (>=1.3.0,<2.0.0)
Requires-Dist: pytest (>=7.4.3,<8.0.0)
Project-URL: Repository, https://github.com/skywinz/pcfl
